README.txt
setup.py
cs/__init__.py
cs.cssbrowserselector.egg-info/PKG-INFO
cs.cssbrowserselector.egg-info/SOURCES.txt
cs.cssbrowserselector.egg-info/dependency_links.txt
cs.cssbrowserselector.egg-info/entry_points.txt
cs.cssbrowserselector.egg-info/namespace_packages.txt
cs.cssbrowserselector.egg-info/not-zip-safe
cs.cssbrowserselector.egg-info/paster_plugins.txt
cs.cssbrowserselector.egg-info/requires.txt
cs.cssbrowserselector.egg-info/top_level.txt
cs/cssbrowserselector/__init__.py
cs/cssbrowserselector/configure.zcml
cs/cssbrowserselector/tests.py
cs/cssbrowserselector/profiles/default/jsregistry.xml
cs/cssbrowserselector/profiles/default/metadata.xml
cs/cssbrowserselector/resources/css_browser_selector.js
cs/cssbrowserselector/resources/css_browser_selector.min.js
docs/HISTORY.txt
docs/INSTALL.txt
docs/LICENSE.GPL
docs/LICENSE.txt