Metadata-Version: 1.1
Name: cs.cssbrowserselector
Version: 1.0
Summary: Add css_browser_selector javascript to Plone
Home-page: http://code.codesyntax.com/private/cs.cssbrowserselector
Author: Mikel Larreategi
Author-email: mlarreategi@codesyntax.com
License: GPL
Keywords: css javascript browser
Platform: UNKNOWN
Classifier: Framework :: Plone
Classifier: Programming Language :: Python
